Metadata-Version: 1.0
Name: hicham
Version: 0.2
Summary: Awesome library
Home-page: UNKNOWN
Author: zekri sidi mohamed hicham
Author-email: h.zekri@esi-sba.dz
License: MIT
Keywords: this is me
Platform: UNKNOWN
